driftguard/__init__.py
driftguard/alert_manager.py
driftguard/visualization.py
driftguard/api/__init__.py
driftguard/api/server.py
driftguard/cli/__init__.py
driftguard/cli/commands.py
driftguard/core/__init__.py
driftguard/core/alert_manager.py
driftguard/core/alerts.py
driftguard/core/config.py
driftguard/core/drift.py
driftguard/core/guardian.py
driftguard/core/interfaces.py
driftguard/core/monitor.py
driftguard/core/state.py
driftguard/core/validation.py
driftguard/utils/__init__.py
driftguard/utils/data_utils.py
driftguard-0.1.6.dist-info/licenses/LICENSE
tests/__init__.py
tests/test_adaptive_threading.py
tests/test_alert_manager.py
tests/test_batch_feature_processing.py
tests/test_batch_processing.py
tests/test_drift_detector.py
tests/test_drift_monitor_wrapper.py
tests/test_driftguard.py
tests/test_example.py
tests/test_model_monitor.py
tests/test_monitor.py
tests/test_version_manager.py
driftguard-0.1.6.dist-info/METADATA
driftguard-0.1.6.dist-info/WHEEL
driftguard-0.1.6.dist-info/top_level.txt
driftguard-0.1.6.dist-info/RECORD
