Metadata-Version: 2.4
Name: driftguard
Version: 0.1.6
License-File: LICENSE
Requires-Dist: numpy
Requires-Dist: pandas
Dynamic: license-file
Dynamic: requires-dist
